monowidget/__init__.py
monowidget/demo.py
monowidget/main.py
monowidget/_utils/__init__.py
monowidget/_utils/const.py
monowidget/_utils/core.py
monowidget/_utils/ordered_dict.py
monowidget/_utils/qcalendar.py
monowidget/_utils/qdatetime.py
monowidget/_utils/qslabel.py
monowidget/_utils/qslider.py
monowidget/_utils/qspacer.py
monowidget/_utils/qtimeedit.py
monowidget/_utils/rangef.py
monowidget/_utils/reset_button.py
monowidget/_utils/validate_components.py
monowidget/inspector/__init__.py
monowidget/inspector/inspector_area.py
monowidget/inspector/mono_attr_item.py
monowidget/inspector/mono_attr_item_base.py
monowidget/inspector/mono_attr_item_bool.py
monowidget/inspector/mono_attr_item_complex.py
monowidget/inspector/mono_attr_item_datetime.py
monowidget/inspector/mono_attr_item_dict.py
monowidget/inspector/mono_attr_item_factory.py
monowidget/inspector/mono_attr_item_float.py
monowidget/inspector/mono_attr_item_function.py
monowidget/inspector/mono_attr_item_int.py
monowidget/inspector/mono_attr_item_list.py
monowidget/inspector/mono_attr_item_str.py
monowidget/inspector/mono_group.py
monowidget/inspector/mono_runtime.py
monowidget/inspector/mono_separator.py
monowidget/inspector/qmono_inspector.py
monowidget/inspector/ui_classes.py
monowidget/inspector/utils.py
monowidget/mono/__init__.py
monowidget/mono/mono.py
monowidget/mono/mono_attr.py
monowidget-0.1.1.dist-info/METADATA
monowidget-0.1.1.dist-info/WHEEL
monowidget-0.1.1.dist-info/top_level.txt
monowidget-0.1.1.dist-info/RECORD
